riplib/__init__.py
riplib/ass.py
riplib/events.py
riplib/models.py
riplib/types.py
riplib-0.1.0.dist-info/METADATA
riplib-0.1.0.dist-info/WHEEL
riplib-0.1.0.dist-info/RECORD
