Metadata-Version: 2.4
Name: riplib
Version: 0.1.0
Summary: A Python 'lib' specializing in fart production.
License: MIT
Keywords: fart,funny,library
Author: hireri
Author-email: hi@aveline.fish
Requires-Python: >=3.8,<4.0
Classifier: License :: OSI Approved :: MIT License
Classifier: Programming Language :: Python :: 3
Classifier: Programming Language :: Python :: 3.8
Classifier: Programming Language :: Python :: 3.9
Classifier: Programming Language :: Python :: 3.10
Classifier: Programming Language :: Python :: 3.11
Classifier: Programming Language :: Python :: 3.12
Classifier: Programming Language :: Python :: 3.13
Classifier: Programming Language :: Python :: 3.14
Project-URL: Homepage, https://github.com/hireri/riplib
Project-URL: Repository, https://github.com/hireri/riplib
